{"cameraMode":{"drawMode":0,"name":"Shaded","section":"Shading Mode"},"sceneLighting":true,"audioPlay":false,"sceneViewState":{"showFog":true,"showMaterialUpdate":false,"showSkybox":true,"showFlares":true,"showImageEffects":true,"showParticleSystems":true},"in2DMode":false,"pivot":{"x":-3.1490955352783205,"y":-3.795956611633301,"z":-5.360629081726074},"rotation":{"x":-0.1190449520945549,"y":0.7108432650566101,"z":-0.12407810986042023,"w":-0.6820090413093567},"size":12.810617446899414,"orthographic":false}